pyanatomogram/__init__.py
pyanatomogram/pyanatomogram.py
pyanatomogram/anatomogram/src/svg/anolis_carolinensis.svg
pyanatomogram/anatomogram/src/svg/arabidopsis_thaliana.svg
pyanatomogram/anatomogram/src/svg/bos_taurus.svg
pyanatomogram/anatomogram/src/svg/brachypodium_distachyon.flower_parts.svg
pyanatomogram/anatomogram/src/svg/brachypodium_distachyon.whole_plant.svg
pyanatomogram/anatomogram/src/svg/gallus_gallus.svg
pyanatomogram/anatomogram/src/svg/homo_sapiens.brain.svg
pyanatomogram/anatomogram/src/svg/homo_sapiens.female.svg
pyanatomogram/anatomogram/src/svg/homo_sapiens.male.svg
pyanatomogram/anatomogram/src/svg/hordeum_vulgare.flower_parts.svg
pyanatomogram/anatomogram/src/svg/hordeum_vulgare.whole_plant.svg
pyanatomogram/anatomogram/src/svg/macaca_mulatta.svg
pyanatomogram/anatomogram/src/svg/monodelphis_domestica.svg
pyanatomogram/anatomogram/src/svg/mus_musculus.brain.svg
pyanatomogram/anatomogram/src/svg/mus_musculus.female.svg
pyanatomogram/anatomogram/src/svg/mus_musculus.male.svg
pyanatomogram/anatomogram/src/svg/oryza_sativa.flower_parts.svg
pyanatomogram/anatomogram/src/svg/oryza_sativa.whole_plant.svg
pyanatomogram/anatomogram/src/svg/papio_anubis.svg
pyanatomogram/anatomogram/src/svg/rattus_norvegicus.svg
pyanatomogram/anatomogram/src/svg/solanum_lycopersicum.flower_parts.svg
pyanatomogram/anatomogram/src/svg/solanum_lycopersicum.whole_plant.svg
pyanatomogram/anatomogram/src/svg/solanum_tuberosum.svg
pyanatomogram/anatomogram/src/svg/sorghum_bicolor.flower_parts.svg
pyanatomogram/anatomogram/src/svg/sorghum_bicolor.whole_plant.svg
pyanatomogram/anatomogram/src/svg/tetraodon_nigroviridis.svg
pyanatomogram/anatomogram/src/svg/triticum_aestivum.flower_parts.svg
pyanatomogram/anatomogram/src/svg/triticum_aestivum.whole_plant.svg
pyanatomogram/anatomogram/src/svg/xenopus_tropicalis.svg
pyanatomogram/anatomogram/src/svg/zea_mays.flower_parts.svg
pyanatomogram/anatomogram/src/svg/zea_mays.whole_plant.svg
pyanatomogram-0.1.1.dist-info/LICENSE
pyanatomogram-0.1.1.dist-info/METADATA
pyanatomogram-0.1.1.dist-info/WHEEL
pyanatomogram-0.1.1.dist-info/top_level.txt
pyanatomogram-0.1.1.dist-info/RECORD
