Metadata-Version: 2.1
Name: pyanatomogram
Version: 0.1.1
Summary: PyAnatomogram is a python package to annotate and highlight organs and tissues in figures
Home-page: https://bitbucket.org/manuela_s/pyanatomogram/
Author: Manuela Salvucci
Author-email: ms@msalvucci.com
License: UNKNOWN
Platform: UNKNOWN
Classifier: Programming Language :: Python :: 3
Classifier: License :: OSI Approved :: BSD License
Classifier: License :: Free To Use But Restricted
Classifier: Operating System :: OS Independent
Requires-Python: >=3.8
License-File: LICENSE
Requires-Dist: lxml
Requires-Dist: matplotlib
Requires-Dist: pandas
Requires-Dist: pylustrator
